setup.py
martian_cli/__init__.py
martian_cli/adapters.py
martian_cli/cli.py
martian_cli/common.py
martian_cli/mro_parser.py
martian_cli.egg-info/PKG-INFO
martian_cli.egg-info/SOURCES.txt
martian_cli.egg-info/dependency_links.txt
martian_cli.egg-info/entry_points.txt
martian_cli.egg-info/requires.txt
martian_cli.egg-info/top_level.txt
test/test_parser.py