Metadata-Version: 1.0
Name: martian-cli
Version: 0.0.3
Summary: An alternate command line interface to 10x Genomics Martian workflows.
Home-page: https://github.com/HumanCellAtlas/skylab/
Author: Marcus Kinsella
Author-email: mkinsella@chanzuckerberg.com
License: UNKNOWN
Platform: UNKNOWN
